skillful_nowcasting/__init__.py
skillful_nowcasting/common.py
skillful_nowcasting/dgmr.py
skillful_nowcasting/discriminators.py
skillful_nowcasting/generators.py
skillful_nowcasting/losses.py
skillful_nowcasting/layers/Attention.py
skillful_nowcasting/layers/ConvGRU.py
skillful_nowcasting/layers/CoordConv.py
skillful_nowcasting/layers/__init__.py
skillful_nowcasting/layers/utils.py
skillful_nowcasting-1.2.3.dist-info/LICENSE
skillful_nowcasting-1.2.3.dist-info/METADATA
skillful_nowcasting-1.2.3.dist-info/WHEEL
skillful_nowcasting-1.2.3.dist-info/top_level.txt
skillful_nowcasting-1.2.3.dist-info/RECORD
